ONENEURON/PERCEPTRON.py
ONENEURON/__init__.py
ON_Package_anishyadav_2021-0.0.2.dist-info/LICENSE
ON_Package_anishyadav_2021-0.0.2.dist-info/METADATA
ON_Package_anishyadav_2021-0.0.2.dist-info/WHEEL
ON_Package_anishyadav_2021-0.0.2.dist-info/top_level.txt
ON_Package_anishyadav_2021-0.0.2.dist-info/RECORD
